{
    "comment": [
        "Generated by: lqn2ps, version 6.0",
        "For: greg",
        "Thu Apr 19:03:33 2017",
        "Invoked as: lqn2ps -Ojson -o. ../regression/13-interlock.in"
    ],
    "general": {
        "comment": "Send interlock with 2-phases and 2 clients.",
        "conv-val": 1e-05,
        "it-limit": 50,
        "underrelax-coeff": 0.9,
        "print-int": 10
    },
    "processor": [
        {
            "name": "p0",
            "scheduling": "fcfs",
            "task": [
                {
                    "name": "t0",
                    "scheduling": "ref",
                    "multiplicity": 2,
                    "entry": [
                        {
                            "name": "e0",
                            "phase": [
                                {
                                    "phase": 1,
                                    "service-time": 1,
                                    "synch-call": [
                                        {
                                            "destination": "e2",
                                            "mean-calls": 1
                                        },
                                        {
                                            "destination": "e1",
                                            "mean-calls": 1
                                        }
                                    ]
                                }
                            ]
                        }
                    ]
                }
            ]
        },
        {
            "name": "p1",
            "scheduling": "fcfs",
            "task": [
                {
                    "name": "t1",
                    "scheduling": "fcfs",
                    "entry": [
                        {
                            "name": "e1",
                            "phase": [
                                {
                                    "phase": 1,
                                    "service-time": 0.5
                                },
                                {
                                    "phase": 2,
                                    "service-time": 0.5,
                                    "synch-call": [
                                        {
                                            "destination": "e2",
                                            "mean-calls": 1
                                        }
                                    ]
                                }
                            ]
                        }
                    ]
                }
            ]
        },
        {
            "name": "p2",
            "scheduling": "fcfs",
            "task": [
                {
                    "name": "t2",
                    "scheduling": "fcfs",
                    "entry": [
                        {
                            "name": "e2",
                            "phase": [
                                {
                                    "phase": 1,
                                    "service-time": 1
                                }
                            ]
                        }
                    ]
                }
            ]
        }
    ]
}
